warrant/__init__.py
warrant/aws_srp.py
warrant/exceptions.py
warrant/tests/__init__.py
warrant/tests/tests.py
warrant_ext-0.6.2.dist-info/LICENSE
warrant_ext-0.6.2.dist-info/METADATA
warrant_ext-0.6.2.dist-info/WHEEL
warrant_ext-0.6.2.dist-info/top_level.txt
warrant_ext-0.6.2.dist-info/zip-safe
warrant_ext-0.6.2.dist-info/RECORD
